ckan-2.11.3-py3.9-nspkg.pth
ckan/__init__.py
ckan/authz.py
ckan/common.py
ckan/exceptions.py
ckan/cli/__init__.py
ckan/cli/asset.py
ckan/cli/clean.py
ckan/cli/cli.py
ckan/cli/config.py
ckan/cli/config_tool.py
ckan/cli/dataset.py
ckan/cli/db.py
ckan/cli/generate.py
ckan/cli/jobs.py
ckan/cli/notify.py
ckan/cli/plugin_info.py
ckan/cli/profile.py
ckan/cli/sass.py
ckan/cli/search_index.py
ckan/cli/server.py
ckan/cli/shell.py
ckan/cli/sysadmin.py
ckan/cli/translation.py
ckan/cli/user.py
ckan/cli/views.py
ckan/config/__init__.py
ckan/config/config_declaration.yaml
ckan/config/deployment.ini_tmpl
ckan/config/environment.py
ckan/config/resource_formats.json
ckan/config/declaration/__init__.py
ckan/config/declaration/describe.py
ckan/config/declaration/key.py
ckan/config/declaration/load.py
ckan/config/declaration/option.py
ckan/config/declaration/serialize.py
ckan/config/declaration/utils.py
ckan/config/middleware/__init__.py
ckan/config/middleware/common_middleware.py
ckan/config/middleware/flask_app.py
ckan/config/solr/schema.xml
ckan/i18n/__init__.py
ckan/i18n/ckan.pot
ckan/i18n/am/LC_MESSAGES/ckan.mo
ckan/i18n/am/LC_MESSAGES/ckan.po
ckan/i18n/ar/LC_MESSAGES/ckan.mo
ckan/i18n/ar/LC_MESSAGES/ckan.po
ckan/i18n/bg/LC_MESSAGES/ckan.mo
ckan/i18n/bg/LC_MESSAGES/ckan.po
ckan/i18n/bs/LC_MESSAGES/ckan.mo
ckan/i18n/bs/LC_MESSAGES/ckan.po
ckan/i18n/ca/LC_MESSAGES/ckan.mo
ckan/i18n/ca/LC_MESSAGES/ckan.po
ckan/i18n/cs_CZ/LC_MESSAGES/ckan.mo
ckan/i18n/cs_CZ/LC_MESSAGES/ckan.po
ckan/i18n/da_DK/LC_MESSAGES/ckan.mo
ckan/i18n/da_DK/LC_MESSAGES/ckan.po
ckan/i18n/de/LC_MESSAGES/ckan.mo
ckan/i18n/de/LC_MESSAGES/ckan.po
ckan/i18n/el/LC_MESSAGES/ckan.mo
ckan/i18n/el/LC_MESSAGES/ckan.po
ckan/i18n/en_AU/LC_MESSAGES/ckan.mo
ckan/i18n/en_AU/LC_MESSAGES/ckan.po
ckan/i18n/en_GB/LC_MESSAGES/ckan.mo
ckan/i18n/en_GB/LC_MESSAGES/ckan.po
ckan/i18n/es/LC_MESSAGES/ckan.mo
ckan/i18n/es/LC_MESSAGES/ckan.po
ckan/i18n/es_AR/LC_MESSAGES/ckan.mo
ckan/i18n/es_AR/LC_MESSAGES/ckan.po
ckan-2.11.3.dist-info/licenses/LICENSE.txt
ckan-2.11.3.dist-info/METADATA
ckan-2.11.3.dist-info/WHEEL
ckan-2.11.3.dist-info/entry_points.txt
ckan-2.11.3.dist-info/namespace_packages.txt
ckan-2.11.3.dist-info/top_level.txt
ckan-2.11.3.dist-info/RECORD
