Metadata-Version: 2.4
Name: ckan
Version: 2.11.3
Summary: CKAN Software
Home-page: http://ckan.org/
Author: https://github.com/ckan/ckan/graphs/contributors
Author-email: info@ckan.org
License: AGPL
Keywords: data,packaging,component,tool,server
Classifier: Development Status :: 5 - Production/Stable
Classifier: License :: OSI Approved :: GNU Affero General Public License v3 or later (AGPLv3+)
Classifier: Programming Language :: Python
Classifier: Programming Language :: Python :: 3.9
Classifier: Programming Language :: Python :: 3.10
Classifier: Programming Language :: Python :: 3.11
Requires-Python: >=3.9
License-File: LICENSE.txt
Requires-Dist: setuptools>=44.1.0
Provides-Extra: requirements
Requires-Dist: alembic==1.13.2; extra == "requirements"
Requires-Dist: async-timeout==4.0.3; extra == "requirements"
Requires-Dist: babel==2.15.0; extra == "requirements"
Requires-Dist: bleach==6.1.0; extra == "requirements"
Requires-Dist: blinker==1.8.2; extra == "requirements"
Requires-Dist: cachelib==0.13.0; extra == "requirements"
Requires-Dist: certifi==2024.7.4; extra == "requirements"
Requires-Dist: charset-normalizer==3.3.2; extra == "requirements"
Requires-Dist: click==8.1.7; extra == "requirements"
Requires-Dist: dominate==2.9.1; extra == "requirements"
Requires-Dist: feedgen==1.0.0; extra == "requirements"
Requires-Dist: flask==3.0.3; extra == "requirements"
Requires-Dist: flask-babel==4.0.0; extra == "requirements"
Requires-Dist: flask-login==0.6.3; extra == "requirements"
Requires-Dist: flask-session==0.8.0; extra == "requirements"
Requires-Dist: flask-wtf==1.2.1; extra == "requirements"
Requires-Dist: greenlet==3.0.3; extra == "requirements"
Requires-Dist: idna==3.7; extra == "requirements"
Requires-Dist: importlib-metadata==8.0.0; extra == "requirements"
Requires-Dist: itsdangerous==2.2.0; extra == "requirements"
Requires-Dist: jinja2==3.1.6; extra == "requirements"
Requires-Dist: lxml==5.2.2; extra == "requirements"
Requires-Dist: mako==1.3.5; extra == "requirements"
Requires-Dist: markdown==3.6; extra == "requirements"
Requires-Dist: markupsafe==2.1.5; extra == "requirements"
Requires-Dist: msgspec==0.18.6; extra == "requirements"
Requires-Dist: mypy==1.10.1; extra == "requirements"
Requires-Dist: mypy-extensions==1.0.0; extra == "requirements"
Requires-Dist: packaging==24.1; extra == "requirements"
Requires-Dist: passlib==1.7.4; extra == "requirements"
Requires-Dist: polib==1.2.0; extra == "requirements"
Requires-Dist: psycopg2==2.9.9; extra == "requirements"
Requires-Dist: pyjwt==2.8.0; extra == "requirements"
Requires-Dist: pyparsing==3.1.2; extra == "requirements"
Requires-Dist: pysolr==3.9.0; extra == "requirements"
Requires-Dist: python-dateutil==2.9.0.post0; extra == "requirements"
Requires-Dist: python-magic==0.4.27; extra == "requirements"
Requires-Dist: pytz==2024.1; extra == "requirements"
Requires-Dist: pyyaml==6.0.1; extra == "requirements"
Requires-Dist: redis==5.0.7; extra == "requirements"
Requires-Dist: requests==2.32.3; extra == "requirements"
Requires-Dist: rq==1.16.2; extra == "requirements"
Requires-Dist: simplejson==3.19.2; extra == "requirements"
Requires-Dist: six==1.16.0; extra == "requirements"
Requires-Dist: sqlalchemy[mypy]==1.4.52; extra == "requirements"
Requires-Dist: sqlalchemy2-stubs==0.0.2a38; extra == "requirements"
Requires-Dist: sqlparse==0.5.0; extra == "requirements"
Requires-Dist: tomli==2.0.1; extra == "requirements"
Requires-Dist: typing-extensions==4.12.2; extra == "requirements"
Requires-Dist: tzlocal==5.2; extra == "requirements"
Requires-Dist: urllib3==2.2.2; extra == "requirements"
Requires-Dist: watchdog==4.0.1; extra == "requirements"
Requires-Dist: webassets==2.0; extra == "requirements"
Requires-Dist: webencodings==0.5.1; extra == "requirements"
Requires-Dist: werkzeug[watchdog]==3.0.6; extra == "requirements"
Requires-Dist: wtforms==3.1.2; extra == "requirements"
Requires-Dist: zipp==3.19.2; extra == "requirements"
Requires-Dist: zope-interface==6.4.post2; extra == "requirements"
Provides-Extra: dev
Requires-Dist: beautifulsoup4==4.12.3; extra == "dev"
Requires-Dist: cookiecutter==2.6.0; extra == "dev"
Requires-Dist: coveralls; extra == "dev"
Requires-Dist: Faker==26.0.0; extra == "dev"
Requires-Dist: factory-boy==3.3.0; extra == "dev"
Requires-Dist: flask-debugtoolbar==0.15.1; extra == "dev"
Requires-Dist: freezegun==1.5.1; extra == "dev"
Requires-Dist: ipdb==0.13.13; extra == "dev"
Requires-Dist: pip-tools==7.4.1; extra == "dev"
Requires-Dist: Pillow==10.4.0; extra == "dev"
Requires-Dist: responses==0.25.3; extra == "dev"
Requires-Dist: sphinx-rtd-theme==2.0.0; extra == "dev"
Requires-Dist: sphinx==7.3.7; extra == "dev"
Requires-Dist: toml==0.10.2; extra == "dev"
Requires-Dist: towncrier==23.11.0; extra == "dev"
Requires-Dist: pytest==8.3.4; extra == "dev"
Requires-Dist: pytest-cov==6.0.0; extra == "dev"
Requires-Dist: pytest-factoryboy==2.7.0; extra == "dev"
Requires-Dist: pytest-freezegun==0.4.2; extra == "dev"
Requires-Dist: pytest-rerunfailures==15.0; extra == "dev"
Requires-Dist: pytest-split==0.10.0; extra == "dev"
Requires-Dist: pytest-retry==1.7.0; extra == "dev"
Requires-Dist: coverage==7.7.1; extra == "dev"
Requires-Dist: junitparser==3.2.0; extra == "dev"
Requires-Dist: junit2html==31.0.2; extra == "dev"
Dynamic: license-file
Dynamic: provides-extra
